{
  "title": "FII Derivative Statistics",
  "report_date": "2026-07-14",
  "report_date_display": "14 Jul 2026",
  "fetched_at_ist": "14 Jul 2026, 10:15 PM IST",
  "source_url": "https://nsearchives.nseindia.com/content/fo/fii_stats_14-Jul-2026.xls",
  "columns": [
    "Category",
    "Buy Contracts",
    "Buy Amount (Cr)",
    "Sell Contracts",
    "Sell Amount (Cr)",
    "OI Contracts",
    "OI Amount (Cr)"
  ],
  "rows": [
    {
      "Category": "Index Futures",
      "Buy Contracts": "7684",
      "Buy Amount (Cr)": "1255.56",
      "Sell Contracts": "18036",
      "Sell Amount (Cr)": "2991.80",
      "OI Contracts": "318807",
      "OI Amount (Cr)": "51297.26"
    },
    {
      "Category": "Index Options",
      "Buy Contracts": "15785843",
      "Buy Amount (Cr)": "2477560.64",
      "Sell Contracts": "16094163",
      "Sell Amount (Cr)": "2525128.55",
      "OI Contracts": "2163724",
      "OI Amount (Cr)": "346294.40"
    },
    {
      "Category": "Stock Futures",
      "Buy Contracts": "300650",
      "Buy Amount (Cr)": "20003.97",
      "Sell Contracts": "382237",
      "Sell Amount (Cr)": "25267.66",
      "OI Contracts": "7021642",
      "OI Amount (Cr)": "465501.37"
    },
    {
      "Category": "Stock Options",
      "Buy Contracts": "275161",
      "Buy Amount (Cr)": "18471.32",
      "Sell Contracts": "277542",
      "Sell Amount (Cr)": "18653.00",
      "OI Contracts": "1219670",
      "OI Amount (Cr)": "81347.78"
    },
    {
      "Category": "Total",
      "Buy Contracts": "16369338",
      "Buy Amount (Cr)": "2517291.49",
      "Sell Contracts": "16771978",
      "Sell Amount (Cr)": "2572041.01",
      "OI Contracts": "10723843",
      "OI Amount (Cr)": "944440.81"
    }
  ]
}